eetc_utils/__init__.py
eetc_utils/clients/__init__.py
eetc_utils/clients/eetc_data.py
eetc_utils/clients/eetc_notifications.py
eetc_utils/finance.py
eetc_utils/options.py
eetc_utils/strategy/__init__.py
eetc_utils/strategy/backtesting/__init__.py
eetc_utils/strategy/backtesting/broker_sim.py
eetc_utils/strategy/backtesting/engine.py
eetc_utils/strategy/backtesting/metrics.py
eetc_utils/strategy/backtesting/strategy.py
eetc_utils/strategy/engine.py
eetc_utils/strategy/strategy.py
eetc_utils-1.3.1.dist-info/METADATA
eetc_utils-1.3.1.dist-info/WHEEL
eetc_utils-1.3.1.dist-info/licenses/LICENSE
eetc_utils-1.3.1.dist-info/RECORD
