Metadata-Version: 2.4
Name: eetc-utils
Version: 1.3.1
Summary: EETC Utils Library
License: MIT
License-File: LICENSE
Author: East Empire Trading Company
Author-email: eastempiretradingcompany2019@gmail.com
Maintainer: East Empire Trading Company
Maintainer-email: eastempiretradingcompany2019@gmail.com
Requires-Python: >=3.12,<4.0
Classifier: License :: OSI Approved :: MIT License
Classifier: Operating System :: OS Independent
Classifier: Programming Language :: Python :: 3
Classifier: Programming Language :: Python :: 3.12
Classifier: Programming Language :: Python :: 3.13
Classifier: Programming Language :: Python :: 3.14
Requires-Dist: arch (>=8.0.0,<9.0.0)
Requires-Dist: numpy (>=2.3.4,<3.0.0)
Requires-Dist: pandas (>=2.3.3,<3.0.0)
Requires-Dist: pytest (>=9.0.1,<10.0.0)
Requires-Dist: requests (>=2.28.0,<3.0.0)
Requires-Dist: setuptools (>=80.9.0,<81.0.0)
Requires-Dist: wheel (>=0.45.1,<0.46.0)
Project-URL: Bug Tracker, https://github.com/east-empire-trading-company/eetc-utils/issues
Project-URL: Homepage, https://github.com/east-empire-trading-company/eetc-utils
Project-URL: Repository, https://github.com/east-empire-trading-company/eetc-utils
